orchestera/__init__.py
orchestera/clients/__init__.py
orchestera/clients/sync_client.py
orchestera/entrypoints/__init__.py
orchestera/entrypoints/base_entrypoint.py
orchestera/entrypoints/run.py
orchestera/entrypoints/sparklith_entrypoint.py
orchestera/kubernetes/__init__.py
orchestera/kubernetes/pod_manager.py
orchestera/kubernetes/pod_spec_builder.py
orchestera/spark/__init__.py
orchestera/spark/session.py
orchestera_lib-0.1.0a2.dist-info/METADATA
orchestera_lib-0.1.0a2.dist-info/WHEEL
orchestera_lib-0.1.0a2.dist-info/top_level.txt
orchestera_lib-0.1.0a2.dist-info/RECORD
