Metadata-Version: 2.4
Name: orchestera-lib
Version: 0.1.0a2
Summary: Orchestera Library
Requires-Python: >=3.10.14
Requires-Dist: PyYAML==6.0.2
Requires-Dist: kubernetes==33.1.0
Requires-Dist: pyspark==3.5.6
Requires-Dist: click==8.1.8
Requires-Dist: tenacity==9.1.2
Requires-Dist: watch==0.2.7
Provides-Extra: dev
Requires-Dist: black; extra == "dev"
Requires-Dist: isort; extra == "dev"
Requires-Dist: pre-commit; extra == "dev"
